async_orch/__init__.py
async_orch-0.1.1.dist-info/licenses/LICENSE
async_orch-0.1.1.dist-info/METADATA
async_orch-0.1.1.dist-info/WHEEL
async_orch-0.1.1.dist-info/top_level.txt
async_orch-0.1.1.dist-info/RECORD
