Metadata-Version: 2.4
Name: async_orch
Version: 0.1.1
Summary: async_orch is a Python library designed for building and managing asynchronous task pipelines.
Author-email: Chakshu <chaks.gautam@gmail.com>
License: MIT License
Project-URL: Homepage, https://github.com/ChakshuGautam/async_orch
Project-URL: Bug Tracker, https://github.com/ChakshuGautam/async_orch/issues
Project-URL: Documentation, https://github.com/ChakshuGautam/async_orch/blob/main/docs/wiki.md
Classifier: Programming Language :: Python :: 3
Classifier: License :: OSI Approved :: MIT License
Classifier: Operating System :: OS Independent
Classifier: Intended Audience :: Developers
Classifier: Topic :: Software Development :: Libraries :: Python Modules
Classifier: Framework :: AsyncIO
Requires-Python: >=3.11
License-File: LICENSE
Requires-Dist: aiobreaker>=0.5.0
Provides-Extra: test
Requires-Dist: pytest>=7.0.0; extra == "test"
Requires-Dist: pytest-asyncio>=0.20.0; extra == "test"
Requires-Dist: backoff>=2.0.0; extra == "test"
Requires-Dist: pytest-cov>=4.0.0; extra == "test"
Dynamic: license-file
